.editorconfig
.gitignore
.nojekyll
.travis.yml
AUTHORS.rst
CONTRIBUTING.rst
HISTORY.rst
LICENSE
MANIFEST.in
Makefile
README.rst
beautify
index.html
setup.cfg
setup.py
test-requirements.txt
tox.ini
.github/ISSUE_TEMPLATE/bug_report.md
.github/ISSUE_TEMPLATE/kifield-feature-request.md
docs/Makefile
docs/authors.rst
docs/conf.py
docs/contributing.rst
docs/example1.png
docs/history.rst
docs/index.rst
docs/installation.rst
docs/make.bat
docs/readme.rst
docs/usage.rst
docs/xess.ico
docs/xess.png
docs/_build/singlehtml/index.html
docs/_build/singlehtml/_images/example1.png
docs/_build/singlehtml/_static/ajax-loader.gif
docs/_build/singlehtml/_static/basic.css
docs/_build/singlehtml/_static/classic.css
docs/_build/singlehtml/_static/comment-bright.png
docs/_build/singlehtml/_static/comment-close.png
docs/_build/singlehtml/_static/comment.png
docs/_build/singlehtml/_static/default.css
docs/_build/singlehtml/_static/doctools.js
docs/_build/singlehtml/_static/down-pressed.png
docs/_build/singlehtml/_static/down.png
docs/_build/singlehtml/_static/file.png
docs/_build/singlehtml/_static/jquery-1.11.1.js
docs/_build/singlehtml/_static/jquery.js
docs/_build/singlehtml/_static/minus.png
docs/_build/singlehtml/_static/plus.png
docs/_build/singlehtml/_static/pygments.css
docs/_build/singlehtml/_static/searchtools.js
docs/_build/singlehtml/_static/sidebar.js
docs/_build/singlehtml/_static/underscore-1.3.1.js
docs/_build/singlehtml/_static/underscore.js
docs/_build/singlehtml/_static/up-pressed.png
docs/_build/singlehtml/_static/up.png
docs/_build/singlehtml/_static/websupport.js
kifield/__init__.py
kifield/__main__.py
kifield/common.py
kifield/dcm.py
kifield/kifield.py
kifield/pckg_info.py
kifield/sch.py
kifield/schlib.py
kifield.egg-info/PKG-INFO
kifield.egg-info/SOURCES.txt
kifield.egg-info/dependency_links.txt
kifield.egg-info/entry_points.txt
kifield.egg-info/not-zip-safe
kifield.egg-info/requires.txt
kifield.egg-info/top_level.txt
tests/integration/__init__.py
tests/integration/randomizer.py
tests/integration/test.mk
tests/integration/kicad5/CAT-cache.lib
tests/integration/kicad5/CAT.pro
tests/integration/kicad5/CAT.sch
tests/integration/kicad5/hier_test-cache.lib
