Metadata-Version: 2.1
Name: kifield
Version: 1.0.1
Summary: Module and utilities for manipulating part fields in KiCad files.
Home-page: https://github.com/devbisme/kifield
Author: Dave Vandenbout
Author-email: devb@xess.com
License: MIT
Project-URL: Documentation, https://devbisme.github.io/KiField
Project-URL: Source, https://github.com/devbisme/kifield
Project-URL: Changelog, https://github.com/devbisme/kifield/blob/master/HISTORY.rst
Project-URL: Tracker, https://github.com/devbisme/kifield/issues
Keywords: kifield KiCad EDA
Classifier: Development Status :: 5 - Production/Stable
Classifier: Intended Audience :: Manufacturing
Classifier: License :: OSI Approved :: MIT License
Classifier: Natural Language :: English
Classifier: Operating System :: OS Independent
Classifier: Programming Language :: Python :: 2.7
Classifier: Programming Language :: Python :: 3
Classifier: Programming Language :: Python :: Implementation :: CPython
Classifier: Topic :: Scientific/Engineering :: Electronic Design Automation (EDA)
License-File: LICENSE
License-File: AUTHORS.rst
